<root>
	<styles>
		<include src="file://{resources}/styles/dotastyles.css" />
		<include src="file://{resources}/styles/popups/popups_shared.css" />
		<include src="file://{resources}/styles/battle_pass/crownfall/bp_crownfall_shared.css" />
		<include src="file://{resources}/styles/popups/popup_dashboard_games.css" />
	</styles>

	<DOTADashboardGamesPopup class="PopupPanel" popupbackground="blur" oncancel="UIPopupButtonClicked()" onactivate="" allows_popups="1">
		<Panel id="CloseButton" onactivate="UIPopupButtonClicked()" />
		<Label id="Header" text="#DOTA_DashboardGames_Title"/>
		<Panel id="DashboardGamesContainer">
			<Panel class="MinigamesRow">
				<Panel class="MinigameButton" onactivate="DOTACrownfallMinigameFishing() UIPopupButtonClicked()">
					<Panel class="Node MainQuestNode EncounterNode fishing" hittest="false">
						<Panel id="NodeBackground" />
						<Panel id="NodeBackgroundInner" hittest="false" />
						<Panel class="NodeIcon Shadow" hittest="false" />
						<Panel class="NodeIcon" hittest="false" />
					</Panel>
					<Label class="MinigameLabel" text="#DOTA_Crownfall_Archive_Minigame_Fishing" />
				</Panel>
				<Panel class="MinigameButton" onactivate="DOTACrownfallMinigameBatRacer() UIPopupButtonClicked()">
					<Panel class="Node MainQuestNode EncounterNode flappy_skywrath_act2" hittest="false">
						<Panel id="NodeBackground" />
						<Panel id="NodeBackgroundInner" hittest="false" />
						<Panel class="NodeIcon Shadow" hittest="false" />
						<Panel class="NodeIcon" hittest="false" />
					</Panel>
					<Label class="MinigameLabel" text="#DOTA_Crownfall_Archive_Minigame_BatRacer" />
				</Panel>
				<Panel class="MinigameButton" onactivate="DOTACrownfallMinigameSleetFighter() UIPopupButtonClicked()">
					<Panel class="Node MainQuestNode EncounterNode fighting" hittest="false">
						<Panel id="NodeBackground" />
						<Panel id="NodeBackgroundInner" hittest="false" />
						<Panel class="NodeIcon Shadow" hittest="false" />
						<Panel class="NodeIcon" hittest="false" />
					</Panel>
					<Label class="MinigameLabel" text="#DOTA_Crownfall_Archive_Minigame_SleetFighter" />
				</Panel>
			</Panel>
			<Panel class="MinigamesRow">
				<Panel class="MinigameButton" onactivate="DOTACrownfallMinigameDragonChess() UIPopupButtonClicked()">
					<Panel class="Node MainQuestNode EncounterNode match_3" hittest="false">
						<Panel id="NodeBackground" />
						<Panel id="NodeBackgroundInner" hittest="false" />
						<Panel class="NodeIcon Shadow" hittest="false" />
						<Panel class="NodeIcon" hittest="false" />
					</Panel>
					<Label class="MinigameLabel" text="#DOTA_Crownfall_Archive_Minigame_DragonChess" />
				</Panel>
				<Panel class="MinigameButton" onactivate="DOTACrownfallMinigameZaugLair() UIPopupButtonClicked()">
					<Panel class="Node MainQuestNode EncounterNode shmup" hittest="false">
						<Panel id="NodeBackground" />
						<Panel id="NodeBackgroundInner" hittest="false" />
						<Panel class="NodeIcon Shadow" hittest="false" />
						<Panel class="NodeIcon" hittest="false" />
					</Panel>
					<Label class="MinigameLabel" text="#DOTA_Crownfall_Archive_Minigame_ZaugsLair" />
				</Panel>
				<Panel class="MinigameButton" onactivate="DOTACrownfallMinigameSpoonMan() UIPopupButtonClicked()">
					<Panel class="Node MainQuestNode EncounterNode techiemen" hittest="false">
						<Panel id="NodeBackground" />
						<Panel id="NodeBackgroundInner" hittest="false" />
						<Panel class="NodeIcon Shadow" hittest="false" />
						<Panel class="NodeIcon" hittest="false" />
					</Panel>
					<Label class="MinigameLabel" text="#DOTA_Crownfall_Archive_Minigame_SpoonMan" />
				</Panel>
			</Panel>
			<Panel class="MinigamesRow">
				<Panel class="MinigameButton" onactivate="DOTACrownfallMinigameCastleCarnage() UIPopupButtonClicked()">
					<Panel class="Node MainQuestNode EncounterNode artillery" hittest="false">
						<Panel id="NodeBackground" />
						<Panel id="NodeBackgroundInner" hittest="false" />
						<Panel class="NodeIcon Shadow" hittest="false" />
						<Panel class="NodeIcon" hittest="false" />
					</Panel>
					<Label class="MinigameLabel" text="#DOTA_Crownfall_Archive_Minigame_CastleCarnage" />
				</Panel>
				<Panel class="MinigameButton" onactivate="DOTACrownfallMinigameSpleenSweeper() UIPopupButtonClicked()">
					<Panel class="Node MainQuestNode EncounterNode minesweeper" hittest="false">
						<Panel id="NodeBackground" />
						<Panel id="NodeBackgroundInner" hittest="false" />
						<Panel class="NodeIcon Shadow" hittest="false" />
						<Panel class="NodeIcon" hittest="false" />
					</Panel>
					<Label class="MinigameLabel" text="#DOTA_Crownfall_Archive_Minigame_SpleenSweeper" />
				</Panel>
				<Panel class="MinigameButton" onactivate="DOTACrownfallMinigameNestOfThorns() UIPopupButtonClicked()">
					<Panel class="Node MainQuestNode EncounterNode survivors" hittest="false">
						<Panel id="NodeBackground" />
						<Panel id="NodeBackgroundInner" hittest="false" />
						<Panel class="NodeIcon Shadow" hittest="false" />
						<Panel class="NodeIcon" hittest="false" />
					</Panel>
					<Label class="MinigameLabel" text="#DOTA_Crownfall_Archive_Minigame_NestOfThorns" />
				</Panel>
			</Panel>
		</Panel>
	</DOTADashboardGamesPopup>
</root>
