<root>
	<styles>
		<include src="file://{resources}/styles/dotastyles.css" />
		<include src="file://{resources}/styles/popups/popups_shared.css" />
		<include src="file://{resources}/styles/battle_pass/crownfall/bp_crownfall_shared.css" />
		<include src="file://{resources}/styles/battle_pass/crownfall/bp_popup_crownfall_tokens_received.css" />
	</styles>

	<Panel class="PopupPanel TokensReceived Hidden" popupbackground="dim" oncancel="UIPopupButtonClicked()">

		<Label class="PopupTitle" text="{s:title}" />
		<Label class="PopupDescription" text="{s:message}" />

		<Panel id="TokenList">
			                
		</Panel>

		<Panel class="ButtonContainer">
			<DOTACrownfallButton text="#DOTA_Crownfall_TokensReceived_Ok" onactivate="UIPopupButtonClicked()" />
		</Panel>

	</Panel>
</root>
