<!-- xml reconstructed by Source 2 Viewer 5.0.0.0 - https://valveresourceformat.github.io -->
<root>
	<styles>
		<include src="s2r://panorama/styles/dotastyles.vcss_c" />
		<include src="s2r://panorama/styles/ui_persona_selector.vcss_c" />
	</styles>
	<DOTAPersonaSelector class="TabGroupContainer">
		<TabButton id="DefaultCosmeticGroupButton" class="TabItem" group="cosmetic_groups" text="#DOTA_Loadout_CosmeticGroup_Default" onactivate="DOTAPersonaSelectorSelected()">
			<DOTAHeroImage id="DefaultHeroIcon" heroimagestyle="icon" class="CosmeticGroupHeroIcon" />
		</TabButton>
		<TabButton id="PersonaCosmeticGroupButton" class="TabItem" group="cosmetic_groups" text="#DOTA_Loadout_CosmeticGroup_Persona" onactivate="DOTAPersonaSelectorSelected()">
			<DOTAHeroImage id="PersonaHeroIcon" heroimagestyle="icon" class="CosmeticGroupHeroIcon" />
		</TabButton>
	</DOTAPersonaSelector>
</root>
